options/common.py
options/data.py
options/download.py
options/headers.py
options/result.py
testing/tests.py
optionsview-0.0.4.dist-info/LICENSE
optionsview-0.0.4.dist-info/METADATA
optionsview-0.0.4.dist-info/WHEEL
optionsview-0.0.4.dist-info/top_level.txt
optionsview-0.0.4.dist-info/RECORD
