Metadata-Version: 2.1
Name: optionsview
Version: 0.0.4
Summary: Download options call/put data for any ticker in a trader friendly format
Home-page: https://github.com/zq99/optionsview
Author: zq99
Author-email: zq99@hotmail.com
License: GPL-3.0+
Keywords: OPTIONS,STRADDLE,DATA,TRADING,CALLS,PUTS,ALGOTRADING,YFINANCE,YAHOO FINANCE,EXPIRATION DATES,SPREADS,STOCK MARKET,TICKER
Classifier: Development Status :: 5 - Production/Stable
Classifier: Intended Audience :: Education
Classifier: Operating System :: Microsoft :: Windows :: Windows 10
Classifier: License :: OSI Approved :: GNU General Public License v3 or later (GPLv3+)
Classifier: Programming Language :: Python :: 3 :: Only
Classifier: Programming Language :: Python :: 3.7
Classifier: Programming Language :: Python :: 3.8
Classifier: Programming Language :: Python :: 3.9
Classifier: Programming Language :: Python :: 3.10
Requires-Python: >=3.7
License-File: LICENSE
Requires-Dist: yfinance
Requires-Dist: pandas
Requires-Dist: numpy
